Workbook

Sheet Summary
A1: Daily Risk & Margin Report
A2: As of 2020-03-23 | compared with 2020-03-20 | 99% confidence | all values in INR
A4: Metric | B4: Previous (2020-03-20) | C4: Today (2020-03-23) | D4: Change | E4: % Change
A5: Portfolio market value | B5: 1090348.1 | C5: 1000000 | D5: =C5-B5 | E5: =IF(OR(B5="",B5=0),"",D5/B5)
A6: 1-day VaR, historical | B6: 28765.972 | C6: 34675.131 | D6: =C6-B6 | E6: =IF(OR(B6="",B6=0),"",D6/B6)
A7: 1-day Expected Shortfall, historical | B7: 51213.903 | C7: 54649.122 | D7: =C7-B7 | E7: =IF(OR(B7="",B7=0),"",D7/B7)
A8: 1-day VaR, parametric | B8: 22152.335 | C8: 21532.067 | D8: =C8-B8 | E8: =IF(OR(B8="",B8=0),"",D8/B8)
A9: 1-day VaR, EWMA | B9: 67521.225 | C9: 73912.815 | D9: =C9-B9 | E9: =IF(OR(B9="",B9=0),"",D9/B9)
A10: VaR limit | B10: 25000 | C10: 25000 | D10: =C10-B10 | E10: =IF(OR(B10="",B10=0),"",D10/B10)
A11: VaR limit utilisation | B11: =B6/B10 | C11: =C6/C10 | D11: =C11-B11
A12: Initial margin, recent calibration | B12: 150968 | C12: 136971.96 | D12: =C12-B12 | E12: =IF(OR(B12="",B12=0),"",D12/B12)
A13: Initial margin, stressed (2020) | B13: 209283.1 | C13: 202762.23 | D13: =C13-B13 | E13: =IF(OR(B13="",B13=0),"",D13/B13)
A14: Initial margin required (APC blend) | B14: 165546.77 | C14: 153419.52 | D14: =C14-B14 | E14: =IF(OR(B14="",B14=0),"",D14/B14)
A15: Collateral after haircuts | B15: 96033.907 | C15: 94300 | D15: =C15-B15 | E15: =IF(OR(B15="",B15=0),"",D15/B15)
A16: Excess / (shortfall) collateral | B16: =B15-B14 | C16: =C15-C14 | D16: =C16-B16 | E16: =IF(OR(B16="",B16=0),"",D16/B16)
A17: Daily P&L | C17: =Positions!I13
A18: VaR exceptions, last 250 days | C18: 9 | D18: YELLOW
A20: Commentary
A21: Status | B21: Comment
A22: INFO | B22: Portfolio value Rs 1,000,000. Daily P&L -Rs 90,348 (-8.3%), driven mainly by RELIANCE.NS (-Rs 30,292, -13.2%).
A23: ALERT | B23: 1-day 99% historical VaR up 20.5% to Rs 34,675 (139% of the Rs 25,000 limit). Largest change in VaR contribution: RELIANCE.NS (-Rs 744). LIMIT BREACH: escalate and consider reducing exposure.
A24: WARNING | B24: EWMA VaR (Rs 73,913) is 113% above historical VaR: recent volatility is elevated, so the 2-year window may understate risk.
A25: ALERT | B25: Initial margin requirement Rs 153,420 (-Rs 12,127 DoD); collateral after haircuts Rs 94,300 (-Rs 1,734 DoD). MARGIN CALL of Rs 59,120 to be issued to the client.
A26: WARNING | B26: VaR EXCEPTION today: loss of Rs 90,348 exceeded yesterday's VaR of Rs 28,766. 9 exceptions in the last 250 days (YELLOW zone).
A27: INFO | B27: Worst stress scenario: 2008-style crisis, loss Rs 279,500 (28.0%). Collateral covers 34% of it, leaving Rs 185,200 of uncollateralised stress exposure.

Sheet Positions
A1: Positions, P&L and VaR contribution
A2: As of 2020-03-23 | compared with 2020-03-20 | 99% confidence | all values in INR
A4: Asset | B4: Class | C4: Units | D4: Price 2020-03-20 | E4: Price 2020-03-23 | F4: Market value | G4: Weight | H4: Daily return | I4: Daily P&L | J4: Standalone VaR | K4: VaR contribution 2020-03-20 | L4: VaR contribution 2020-03-23 | M4: Change in contribution
A5: RELIANCE.NS | B5: Equity | C5: 508.04956 | D5: 453.28729 | E5: 393.66238 | F5: =C5*E5 | G5: =F5/$F$13 | H5: =E5/D5-1 | I5: =C5*(E5-D5) | J5: 9492.7167 | K5: 8377.808 | L5: 7634.1928 | M5: =L5-K5
A6: HDFCBANK.NS | B6: Equity | C6: 417.30243 | D6: 411.30426 | E6: 359.45154 | F6: =C6*E6 | G6: =F6/$F$13 | H6: =E6/D6-1 | I6: =C6*(E6-D6) | J6: 5133.7158 | K6: 2992.9869 | L6: 3100.6713 | M6: =L6-K6
A7: TCS.NS | B7: Equity | C7: 105.33459 | D7: 1532.9877 | E7: 1424.0337 | F7: =C7*E7 | G7: =F7/$F$13 | H7: =E7/D7-1 | I7: =C7*(E7-D7) | J7: 5948.7663 | K7: 3894.0796 | L7: 3796.3302 | M7: =L7-K7
A8: INFY.NS | B8: Equity | C8: 225.84589 | D8: 492.19257 | E8: 442.77982 | F8: =C8*E8 | G8: =F8/$F$13 | H8: =E8/D8-1 | I8: =C8*(E8-D8) | J8: 4323.6606 | K8: 2643.2023 | L8: 2592.4167 | M8: =L8-K8
A9: NIFTYBEES.NS | B9: Equity | C9: 1795.9771 | D9: 92.970001 | E9: 83.519997 | F9: =C9*E9 | G9: =F9/$F$13 | H9: =E9/D9-1 | I9: =C9*(E9-D9) | J9: 3913.7655 | K9: 3174.7071 | L9: 3196.9821 | M9: =L9-K9
A10: GOLDBEES.NS | B10: Gold | C10: 2855.5111 | D10: 36.110001 | E10: 35.02 | F10: =C10*E10 | G10: =F10/$F$13 | H10: =E10/D10-1 | I10: =C10*(E10-D10) | J10: 1913.4427 | K10: 45.344082 | L10: 183.25317 | M10: =L10-K10
A11: SETF10GILT.NS | B11: Bonds | C11: 526.70389 | D11: 182.27 | E11: 189.86 | F11: =C11*E11 | G11: =F11/$F$13 | H11: =E11/D11-1 | I11: =C11*(E11-D11) | J11: 5805.7904 | K11: 1036.4446 | L11: 1048.7158 | M11: =L11-K11
A12: INR=X | B12: FX | C12: 661.18237 | D12: 75.159698 | E12: 75.622101 | F12: =C12*E12 | G12: =F12/$F$13 | H12: =E12/D12-1 | I12: =C12*(E12-D12) | J12: 613.82157 | K12: -12.237264 | L12: -20.494678 | M12: =L12-K12
A13: TOTAL | F13: =SUM(F5:F12) | G13: =SUM(G5:G12) | H13: =I13/SUMPRODUCT(C5:C12,D5:D12) | I13: =SUM(I5:I12) | J13: =SUM(J5:J12) | K13: =SUM(K5:K12) | L13: =SUM(L5:L12) | M13: =SUM(M5:M12)
A15: Diversification benefit (standalone VaR sum - parametric VaR) | J15: =J13-L13
A16: VaR contributions are component VaRs: they add up to the parametric VaR. Positive change = asset added risk today.

Sheet Margin
A1: Initial margin and collateral
A2: As of 2020-03-23 | compared with 2020-03-20 | 99% confidence | all values in INR
A4: Initial margin (10-day MPOR) | B4: Previous (2020-03-20) | C4: Today (2020-03-23) | D4: Change
A5: Recent (last 2y) | B5: 150968 | C5: 136971.96 | D5: =C5-B5
A6: Stressed (2020) | B6: 209283.1 | C6: 202762.23 | D6: =C6-B6
A7: APC blend (25% stressed) | B7: 165546.77 | C7: 153419.52 | D7: =C7-B7
A8: sqrt(10) x 1-day VaR (recent) | B8: 90965.989 | C8: 109652.39 | D8: =C8-B8
A10: IM by asset class (today) | B10: Standalone IM
A11: Bonds | B11: 12405.969
A12: Equity | B12: 139418.16
A13: FX | B13: 1530.1108
A14: Gold | B14: 5074.308
A16: Collateral (today) | B16: Price driver | C16: Units | D16: Price | E16: Market value | F16: Haircut | G16: Value after haircut
A17: Cash (INR) | B17: - | E17: 40000 | F17: 0 | G17: =E17*(1-F17)
A18: Government bonds | B18: SETF10GILT.NS | C18: 158.01117 | D18: 189.86 | E18: =C18*D18 | F18: 0.04 | G18: =E18*(1-F18)
A19: Nifty 50 ETF units | B19: NIFTYBEES.NS | C19: 359.19542 | D19: 83.519997 | E19: =C19*D19 | F19: 0.15 | G19: =E19*(1-F19)
A20: TOTAL | E20: =SUM(E17:E19) | G20: =SUM(G17:G19)
A22: Initial margin required (APC blend) | G22: =C7
A23: Excess / (shortfall) collateral | G23: =G20-G22

Sheet Stress
A1: Stress tests on today's portfolio
A2: As of 2020-03-23 | compared with 2020-03-20 | 99% confidence | all values in INR
A4: Scenario | B4: Type | C4: P&L | D4: % of portfolio | E4: x 1-day VaR | F4: Covered by collateral
A5: 2008-style crisis | B5: Hypothetical | C5: -279500 | D5: -0.2795 | E5: =IF(C5<0,-C5/Summary!C6,0) | F5: =IF(C5<0,MIN(1,Summary!C15/-C5),"")
A6: COVID-19 crash (Feb-Mar 2020) | B6: Historical | C6: -262425.79 | D6: -0.26242579 | E6: =IF(C6<0,-C6/Summary!C6,0) | F6: =IF(C6<0,MIN(1,Summary!C15/-C6),"")
A7: Equity crash -20% | B7: Hypothetical | C7: -140500 | D7: -0.1405 | E7: =IF(C7<0,-C7/Summary!C6,0) | F7: =IF(C7<0,MIN(1,Summary!C15/-C7),"")
A8: Hedges fail (everything falls) | B8: Hypothetical | C8: -130000 | D8: -0.13 | E8: =IF(C8<0,-C8/Summary!C6,0) | F8: =IF(C8<0,MIN(1,Summary!C15/-C8),"")
A9: Rate shock (+150bp yields) | B9: Hypothetical | C9: -88500 | D9: -0.0885 | E9: =IF(C9<0,-C9/Summary!C6,0) | F9: =IF(C9<0,MIN(1,Summary!C15/-C9),"")
A10: IL&FS crisis (Aug-Oct 2018) | B10: Historical | C10: -87264.567 | D10: -0.087264567 | E10: =IF(C10<0,-C10/Summary!C6,0) | F10: =IF(C10<0,MIN(1,Summary!C15/-C10),"")

Sheet VaR history
A1: VaR vs actual P&L, last 60 days
A2: As of 2020-03-23 | compared with 2020-03-20 | 99% confidence | all values in INR
A4: Date | B4: Actual P&L | C4: Loss | D4: Historical VaR | E4: Parametric VaR | F4: EWMA VaR | G4: Exception
A5: 43826 | B5: -567.55376 | C5: =MAX(0,-B5) | D5: 14908.702 | E5: 15385.847 | F5: 11333.474 | G5: =IF(C5>D5,"YES","")
A6: 43829 | B6: 746.18385 | C6: =MAX(0,-B6) | D6: 14908.702 | E6: 15383.928 | F6: 10992.969 | G6: =IF(C6>D6,"YES","")
A7: 43830 | B7: -11912.335 | C7: =MAX(0,-B7) | D7: 14908.702 | E7: 15369.203 | F7: 10666.557 | G7: =IF(C7>D7,"YES","")
A8: 43831 | B8: 1366.1936 | C8: =MAX(0,-B8) | D8: 14908.702 | E8: 15425.699 | F8: 12370.408 | G8: =IF(C8>D8,"YES","")
A9: 43832 | B9: 6354.8169 | C9: =MAX(0,-B9) | D9: 14908.702 | E9: 15425.795 | F9: 12018.796 | G9: =IF(C9>D9,"YES","")
A10: 43833 | B10: 2844.0023 | C10: =MAX(0,-B10) | D10: 14908.702 | E10: 15433.606 | F10: 12202.356 | G10: =IF(C10>D10,"YES","")
A11: 43836 | B11: -10184.98 | C11: =MAX(0,-B11) | D11: 14908.702 | E11: 15433.759 | F11: 11941.107 | G11: =IF(C11>D11,"YES","")
A12: 43837 | B12: 3758.8674 | C12: =MAX(0,-B12) | D12: 14908.702 | E12: 15476.037 | F12: 12950.615 | G12: =IF(C12>D12,"YES","")
A13: 43838 | B13: 5141.2927 | C13: =MAX(0,-B13) | D13: 14908.702 | E13: 15477.315 | F13: 12737.473 | G13: =IF(C13>D13,"YES","")
A14: 43839 | B14: 3625.436 | C14: =MAX(0,-B14) | D14: 14908.702 | E14: 15483.461 | F14: 12692.193 | G14: =IF(C14>D14,"YES","")
A15: 43840 | B15: -1395.9053 | C15: =MAX(0,-B15) | D15: 14908.702 | E15: 15469.09 | F15: 12477.749 | G15: =IF(C15>D15,"YES","")
A16: 43843 | B16: 6961.2612 | C16: =MAX(0,-B16) | D16: 14908.702 | E16: 15470.615 | F16: 12123.749 | G16: =IF(C16>D16,"YES","")
... A64: 43913 | B64: -79712.04 | C64: =MAX(0,-B64) | D64: 24234.199 | E64: 19870.66 | F64: 60140.531 | G64: =IF(C64>D64,"YES","")

Sheet Backtest
A1: Historical VaR backtest, last 250 days
A2: As of 2020-03-23 | compared with 2020-03-20 | 99% confidence | all values in INR
A4: Exceptions | B4: 9
A5: Expected | B5: 2.5
A6: Basel zone | B6: YELLOW
A7: Kupiec p-value | B7: 0.001
A8: Christoffersen p-value | B8: 0.024
A10: Exception date | B10: Actual P&L | C10: VaR forecast | D10: Excess loss
A11: 43622 | B11: -19499.557 | C11: 12981.666 | D11: =-B11-C11
A12: 43760 | B12: -17121.867 | C12: 13981.7 | D12: =-B12-C12
A13: 43889 | B13: -34666.609 | C13: 14908.702 | D13: =-B13-C13
A14: 43899 | B14: -43703.815 | C14: 15868.732 | D14: =-B14-C14
A15: 43902 | B15: -59633.973 | C15: 17145.644 | D15: =-B15-C15
A16: 43906 | B16: -54677.005 | C16: 19504.529 | D16: =-B16-C16
A17: 43907 | B17: -22179.211 | C17: 20143.512 | D17: =-B17-C17
A18: 43908 | B18: -24128.821 | C18: 22304.085 | D18: =-B18-C18
A19: 43913 | B19: -79712.04 | C19: 24234.199 | D19: =-B19-C19
